odoo/addons/report_xlsx_helper/README.rst
odoo/addons/report_xlsx_helper/__init__.py
odoo/addons/report_xlsx_helper/__manifest__.py
odoo/addons/report_xlsx_helper/controllers/__init__.py
odoo/addons/report_xlsx_helper/controllers/main.py
odoo/addons/report_xlsx_helper/i18n/ca.po
odoo/addons/report_xlsx_helper/i18n/es.po
odoo/addons/report_xlsx_helper/i18n/fr.po
odoo/addons/report_xlsx_helper/i18n/it.po
odoo/addons/report_xlsx_helper/i18n/report_xlsx_helper.pot
odoo/addons/report_xlsx_helper/i18n/tr.po
odoo/addons/report_xlsx_helper/models/__init__.py
odoo/addons/report_xlsx_helper/models/ir_actions_report.py
odoo/addons/report_xlsx_helper/readme/CONTRIBUTORS.md
odoo/addons/report_xlsx_helper/readme/DESCRIPTION.md
odoo/addons/report_xlsx_helper/readme/INSTALL.md
odoo/addons/report_xlsx_helper/readme/USAGE.md
odoo/addons/report_xlsx_helper/report/__init__.py
odoo/addons/report_xlsx_helper/report/report_xlsx_abstract.py
odoo/addons/report_xlsx_helper/report/report_xlsx_format.py
odoo/addons/report_xlsx_helper/report/test_partner_report_xlsx.py
odoo/addons/report_xlsx_helper/static/description/icon.png
odoo/addons/report_xlsx_helper/static/description/index.html
odoo/addons/report_xlsx_helper/tests/__init__.py
odoo/addons/report_xlsx_helper/tests/test_report_xlsx_helper.py
odoo_addon_report_xlsx_helper-18.0.1.0.0.4.dist-info/METADATA
odoo_addon_report_xlsx_helper-18.0.1.0.0.4.dist-info/WHEEL
odoo_addon_report_xlsx_helper-18.0.1.0.0.4.dist-info/top_level.txt
odoo_addon_report_xlsx_helper-18.0.1.0.0.4.dist-info/RECORD
